Workbook

Sheet Summary P&L
B2: Proposed Carpet | C2: =C18/1.2 -> 2373.2933 | D2: =D18/1.2 -> 2700.6441 | E2: =E18/1.2 -> 2782.4818 | F2: =F18/1.2 -> 2864.3195 | G2: =G18/1.2 -> 2946.1572
B3: Additional Area in Carpet | C3: =C16*C4/1.2 -> 736.5393 | D3: =D16*D4/1.2 -> 1063.8901 | E3: =E16*E4/1.2 -> 1145.7278 | F3: =F16*F4/1.2 -> 1227.5655 | G3: =G16*G4/1.2 -> 1309.4032
C4: 0.45 | D4: 0.65 | E4: 0.7 | F4: 0.75 | G4: 0.8 | L4: 0.45 | M4: 0.65 | N4: 0.7 | O4: 0.75 | P4: 0.8
B5: Particulars | C5: ='Feasibility Report'!O3 -> "45% additional area | D5: ='Feasibility Report'!Q3 -> "65% additional area | E5: ='Feasibility Report'!R3 -> "70% additioanl area | F5: ='Feasibility Report'!S3 -> "75% additional area | G5: ='Feasibility Report'!T3 -> "80% additional area | L5: "45% additional area | M5: "65% additional area | N5: "70% additioanl area | O5: "75% additional area | P5: "80% additional area
B6: AREA OF PLOT | C6: ='Feasibility Report'!O5 -> 1538.9 | D6: ='Feasibility Report'!Q5 -> 1538.9 | E6: ='Feasibility Report'!R5 -> 1538.9 | F6: ='Feasibility Report'!S5 -> 1538.9 | G6: ='Feasibility Report'!T5 -> 1538.9 | J6: Sale area in Sq ft | L6: =C26 -> 53449.21 | M6: =D26 -> 49605.278 | N6: =E26 -> 48644.295 | O6: =F26 -> 47683.312 | P6: =G26 -> 46722.33
B7: AREA OF PLOT IN POSSESSION | C7: ='Feasibility Report'!O6 -> 1538.9 | D7: ='Feasibility Report'!Q6 -> 1538.9 | E7: ='Feasibility Report'!R6 -> 1538.9 | F7: ='Feasibility Report'!S6 -> 1538.9 | G7: ='Feasibility Report'!T6 -> 1538.9
B8: ='Feasibility Report'!M13 -> New Net Plot Area | C8: ='Feasibility Report'!N13 -> 1465.9 | D8: ='Feasibility Report'!N13 -> 1465.9 | E8: ='Feasibility Report'!N13 -> 1465.9 | F8: ='Feasibility Report'!N13 -> 1465.9 | G8: ='Feasibility Report'!N13 -> 1465.9 | J8: Sale Proceeds
J9: Residential @ 55000 | L9: =L6*55000/10000000 -> 293.97065 | M9: =M6*55000/10000000 -> 272.82903 | N9: =N6*55000/10000000 -> 267.54362 | O9: =O6*55000/10000000 -> 262.25822 | P9: =P6*55000/10000000 -> 256.97281 | Q9: =L9*10000000/L6 -> 55000
B10: Existing BUA | C10: ='Feasibility Report'!N15 -> 1634.33 | D10: ='Feasibility Report'!N15 -> 1634.33 | E10: ='Feasibility Report'!N15 -> 1634.33 | F10: ='Feasibility Report'!N15 -> 1634.33 | G10: ='Feasibility Report'!N15 -> 1634.33 | J10: Commercial
J11: Parking Revenue @INR 25 lakhs | L11: =90*2500000/10000000 -> 22.5 | M11: =L11 -> 22.5 | N11: =M11 -> 22.5 | O11: =N11 -> 22.5 | P11: =O11 -> 22.5 | Q11: Assumed 90 parkings
B12: Existing Balcony Area | C12: ='Feasibility Report'!O17 -> 129.329 | D12: ='Feasibility Report'!O17 -> 129.329 | E12: ='Feasibility Report'!O17 -> 129.329 | F12: ='Feasibility Report'!O17 -> 129.329 | G12: ='Feasibility Report'!O17 -> 129.329 | L12: =SUM(L9:L11) -> 316.47065 | M12: =SUM(M9:M11) -> 295.32903 | N12: =SUM(N9:N11) -> 290.04362 | O12: =SUM(O9:O11) -> 284.75822 | P12: =SUM(P9:P11) -> 279.47281
B13: Existing CA Residential Flats: 33 | C13: ='Feasibility Report'!O18 -> 1498.33 | D13: ='Feasibility Report'!O18 -> 1498.33 | E13: ='Feasibility Report'!O18 -> 1498.33 | F13: ='Feasibility Report'!O18 -> 1498.33 | G13: ='Feasibility Report'!O18 -> 1498.33
B14: Existing CA Commercial Shops: 4 | C14: ='Feasibility Report'!O19 -> 138.424 | D14: ='Feasibility Report'!O19 -> 138.424 | E14: ='Feasibility Report'!O19 -> 138.424 | F14: ='Feasibility Report'!O19 -> 138.424 | G14: ='Feasibility Report'!O19 -> 138.424 | J14: Construction area | K14: Sq ft | L14: =C22*1.35*10.764 -> 120756.81 | M14: =D22*1.35*10.764 -> 120756.81 | N14: =E22*1.35*10.764 -> 120756.81 | O14: =F22*1.35*10.764 -> 120756.81 | P14: =G22*1.35*10.764 -> 120756.81
B15: Total Existing Carpet Area | C15: =C13+C14 -> 1636.754 | D15: =D13+D14 -> 1636.754 | E15: =E13+E14 -> 1636.754 | F15: =F13+F14 -> 1636.754 | G15: =G13+G14 -> 1636.754 | J15: (total BUA * 1.35 times)
B16: Existing BUA with balcony (1636.75 * 1.2) | C16: =C15*1.2 -> 1964.1048 | D16: =D15*1.2 -> 1964.1048 | E16: =E15*1.2 -> 1964.1048 | F16: =F15*1.2 -> 1964.1048 | G16: =G15*1.2 -> 1964.1048 | H16: Rate need to discuss with MS | J16: Constr. Cost @INR 4720 (including GST) | K16: =L14 -> 120756.81 | L16: =K16*4720/10000000 -> 56.997212 | M16: =L16 -> 56.997212 | N16: =M16 -> 56.997212 | O16: =N16 -> 56.997212 | P16: =O16 -> 56.997212 | Q16: =L16/3 -> 18.999071 | R16: =M16/3 -> 18.999071 | S16: =N16/3 -> 18.999071 | T16: =O16/3 -> 18.999071 | U16: =P16/3 -> 18.999071
H17: Rate need to discuss with MS | J17: Podium parking RCC work@INR 2950 | K17: 35779.79 | L17: =35780*2950/10000000 -> 10.5551 | M17: =L17 -> 10.5551 | N17: =M17 -> 10.5551 | O17: =N17 -> 10.5551 | P17: =O17 -> 10.5551 | Q17: =L17/3 -> 3.5183667 | R17: =M17/3 -> 3.5183667 | S17: =N17/3 -> 3.5183667 | T17: =O17/3 -> 3.5183667 | U17: =P17/3 -> 3.5183667
A18: A | B18: Proposed BUA Rehab ( Existing builtup area * additional area offered) | C18: =C16*(1+C4) -> 2847.952 | D18: =D16*(1+D4) -> 3240.7729 | E18: =E16*(1+E4) -> 3338.9782 | F18: =F16*(1+F4) -> 3437.1834 | G18: =G16*(1+G4) -> 3535.3886 | J18: Cost Escalation @ 5% | L18: =(L16+L17)*0.05 -> 3.3776156 | M18: =(M16+M17)*0.05 -> 3.3776156 | N18: =(N16+N17)*0.05 -> 3.3776156 | O18: =(O16+O17)*0.05 -> 3.3776156 | P18: =(P16+P17)*0.05 -> 3.3776156 | Q18: =L18/3 -> 1.1258719 | R18: =M18/3 -> 1.1258719 | S18: =N18/3 -> 1.1258719 | T18: =O18/3 -> 1.1258719 | U18: =P18/3 -> 1.1258719
J19: Construction cost 6% | L19: =((120757*4000)+(35780*2500))*6%/10000000 -> 3.434868 | M19: =((120757*4000)+(35780*2500))*6%/10000000 -> 3.434868 | N19: =((120757*4000)+(35780*2500))*6%/10000000 -> 3.434868 | O19: =((120757*4000)+(35780*2500))*6%/10000000 -> 3.434868 | P19: =((120757*4000)+(35780*2500))*6%/10000000 -> 3.434868 | Q19: =L19/3 -> 1.144956 | R19: =M19/3 -> 1.144956 | S19: =N19/3 -> 1.144956 | T19: =O19/3 -> 1.144956 | U19: =P19/3 -> 1.144956
A20: Main | B20: Total BUA proposed (plot area in Posession*4) | C20: =C7*4 -> 6155.6 | D20: =D7*4 -> 6155.6 | E20: =E7*4 -> 6155.6 | F20: =F7*4 -> 6155.6 | G20: =G7*4 -> 6155.6 | J20: TDR cost- 881.17 sq mt @ INR 122580 | L20: =('Feasibility Report'!T65+'Feasibility Report'!T66)/10000000 -> 7.4529535 | M20: =L20 -> 7.4529535 | N20: =M20 -> 7.4529535 | O20: =N20 -> 7.4529535 | P20: =O20 -> 7.4529535 | Q20: =L20 -> 7.4529535 | R20: =M20 -> 7.4529535 | S20: =N20 -> 7.4529535 | T20: =O20 -> 7.4529535 | U20: =P20 -> 7.4529535
B21: Fungible area (Proposed BUA * 0.35) | C21: =C20*0.35 -> 2154.46 | D21: =D20*0.35 -> 2154.46 | E21: =E20*0.35 -> 2154.46 | F21: =F20*0.35 -> 2154.46 | G21: =G20*0.35 -> 2154.46 | J21: SD on TDR @ 3% | L21: =L20*3% -> 0.2235886 | M21: =M20*3% -> 0.2235886 | N21: =N20*3% -> 0.2235886 | O21: =O20*3% -> 0.2235886 | P21: =P20*3% -> 0.2235886 | Q21: =L21 -> 0.2235886 | R21: =M21 -> 0.2235886 | S21: =N21 -> 0.2235886 | T21: =O21 -> 0.2235886 | U21: =P21 -> 0.2235886
A22: B | B22: Total BUA with fungible | C22: =C20+C21 -> 8310.06 | D22: =D20+D21 -> 8310.06 | E22: =E20+E21 -> 8310.06 | F22: =F20+F21 -> 8310.06 | G22: =G20+G21 -> 8310.06 | H22: =C22/C7 -> 5.4 | J22: 50 % Government FSI @INR 122580 | K22: 732.95 | L22: =(K22*122580*0.5)/10000000 -> 4.4922505 | M22: =(K22*122580*0.5)/10000000 -> 4.4922505 | N22: =(K22*122580*0.5)/10000000 -> 4.4922505 | O22: =(K22*122580*0.5)/10000000 -> 4.4922505 | P22: =(K22*122580*0.5)/10000000 -> 4.4922505 | Q22: =L22 -> 4.4922505 | R22: =M22 -> 4.4922505 | S22: =N22 -> 4.4922505 | T22: =O22 -> 4.4922505 | U22: =P22 -> 4.4922505
J23: Cost of Sale Fungible Area Rest @INR 122580 | K23: 1582.4445 | L23: =(K23*122580*0.5)/10000000 -> 9.6988023 | M23: =(K23*122580*0.5)/10000000 -> 9.6988023 | N23: =(K23*122580*0.5)/10000000 -> 9.6988023 | O23: =(K23*122580*0.5)/10000000 -> 9.6988023 | P23: =(K23*122580*0.5)/10000000 -> 9.6988023 | Q23: =L23 -> 9.6988023 | R23: =M23 -> 9.6988023 | S23: =N23 -> 9.6988023 | T23: =O23 -> 9.6988023 | U23: =P23 -> 9.6988023
B24: Sale BUA (B-A) | C24: =C22-C18 -> 5462.108 | D24: =D22-D18 -> 5069.2871 | E24: =E22-E18 -> 4971.0818 | F24: =F22-F18 -> 4872.8766 | G24: =G22-G18 -> 4774.6714 | J24: Commercial sale fungible area
B25: Sale Carpert area (BUA/1.1) | C25: =C24/1.1 -> 4965.5528 | D25: =D24/1.1 -> 4608.4428 | E25: =E24/1.1 -> 4519.1653 | F25: =F24/1.1 -> 4429.8878 | G25: =G24/1.1 -> 4340.6103 | J25: PAP purchase cost approx @ INR 1.7 lakhs | K25: 1245.72 | L25: =K25*170000/10000000 -> 21.17724 | M25: =K25*170000/10000000 -> 21.17724 | N25: =K25*170000/10000000 -> 21.17724 | O25: =K25*170000/10000000 -> 21.17724 | P25: =K25*170000/10000000 -> 21.17724 | Q25: =L25 -> 21.17724 | R25: =M25 -> 21.17724 | S25: =N25 -> 21.17724 | T25: =O25 -> 21.17724 | U25: =P25 -> 21.17724
B26: Sale Carpert area in sq ft | C26: =C25*10.764 -> 53449.21 | D26: =D25*10.764 -> 49605.278 | E26: =E25*10.764 -> 48644.295 | F26: =F25*10.764 -> 47683.312 | G26: =G25*10.764 -> 46722.33 | J26: Stamp duty on PAP @ 6% | K26: 0 | L26: =L25*6% -> 1.2706344 | M26: =M25*6% -> 1.2706344 | N26: =N25*6% -> 1.2706344 | O26: =O25*6% -> 1.2706344 | P26: =P25*6% -> 1.2706344 | Q26: =L26 -> 1.2706344 | R26: =M26 -> 1.2706344 | S26: =N26 -> 1.2706344 | T26: =O26 -> 1.2706344 | U26: =P26 -> 1.2706344
J27: Difference in premium RR approx @ INR 20000 | K27: 1245.72 | L27: =K27*20000*0.4/10000000 -> 0.996576 | M27: =K27*20000*0.4/10000000 -> 0.996576 | N27: =K27*20000*0.4/10000000 -> 0.996576 | O27: =K27*20000*0.4/10000000 -> 0.996576 | P27: =K27*20000*0.4/10000000 -> 0.996576 | Q27: =L27 -> 0.996576 | R27: =M27 -> 0.996576 | S27: =N27 -> 0.996576 | T27: =O27 -> 0.996576 | U27: =P27 -> 0.996576
C28: Units | D28: Sq ft | J28: Muncipal Exp
B29: Residential | C29: 33 | D29: ='Feasibility Report'!O18*10.764 -> 16128.024 | J29: Scrutiny fees (Total BUA with fungible FSI) * RR | L29: ='Feasibility Report'!T75/10000000 -> 0.2493018 | M29: =L29 -> 0.2493018 | N29: =M29 -> 0.2493018 | O29: =N29 -> 0.2493018 | P29: =O29 -> 0.2493018 | Q29: =L29 -> 0.2493018 | R29: =M29 -> 0.2493018 | S29: =N29 -> 0.2493018 | T29: =O29 -> 0.2493018 | U29: =P29 -> 0.2493018
B30: Commercial | C30: 4 | D30: ='Feasibility Report'!O19*10.764 -> 1489.9959 | J30: I.O.D Deposit | L30: ='Feasibility Report'!T76/10000000 -> 0.0089448785 | M30: =L30 -> 0.0089448785 | N30: =M30 -> 0.0089448785 | O30: =N30 -> 0.0089448785 | P30: =O30 -> 0.0089448785 | Q30: =L30 -> 0.0089448785 | R30: =M30 -> 0.0089448785 | S30: =N30 -> 0.0089448785 | T30: =O30 -> 0.0089448785 | U30: =P30 -> 0.0089448785
C31: =SUM(C29:C30) -> 37 | D31: =SUM(D29:D30) -> 17618.02 | J31: Debris Deposit (Rs. 45,000 max) | L31: ='Feasibility Report'!T77/10000000 -> 0.0045 | M31: =L31 -> 0.0045 | N31: =M31 -> 0.0045 | O31: =N31 -> 0.0045 | P31: =O31 -> 0.0045 | Q31: =L31 -> 0.0045 | R31: =M31 -> 0.0045 | S31: =N31 -> 0.0045 | T31: =O31 -> 0.0045 | U31: =P31 -> 0.0045
J32: Development charges 4% for built up area | L32: ='Feasibility Report'!T78/10000000 -> 3.9605633 | M32: =L32 -> 3.9605633 | N32: =M32 -> 3.9605633 | O32: =N32 -> 3.9605633 | P32: =O32 -> 3.9605633 | Q32: =L32 -> 3.9605633 | R32: =M32 -> 3.9605633 | S32: =N32 -> 3.9605633 | T32: =O32 -> 3.9605633 | U32: =P32 -> 3.9605633
B33: Rental ( Higher side) | C33: Per Sq ft | D33: Y1 | E33: Y2 | F33: Y3 | J33: Dev charges on commercial area | L33: ='Feasibility Report'!T79/10000000 -> 0 | M33: =L33 -> 0 | N33: =M33 -> 0 | O33: =N33 -> 0 | P33: =O33 -> 0 | Q33: =L33 -> 0 | R33: =M33 -> 0 | S33: =N33 -> 0 | T33: =O33 -> 0 | U33: =P33 -> 0
B34: Residential | C34: 150 | D34: =D29*C34*12 -> 29030443 | E34: =D34*1.1 -> 31933488 | F34: =E34*1.1 -> 35126837 | J34: Development charges 1% of land component (New Plot area * 1%) | L34: ='Feasibility Report'!T80/10000000 -> 0.17969002 | M34: =L34 -> 0.17969002 | N34: =M34 -> 0.17969002 | O34: =N34 -> 0.17969002 | P34: =O34 -> 0.17969002 | Q34: =L34 -> 0.17969002 | R34: =M34 -> 0.17969002 | S34: =N34 -> 0.17969002 | T34: =O34 -> 0.17969002 | U34: =P34 -> 0.17969002
B35: Commercial | C35: 300 | D35: =D30*C35*12 -> 5363985.4 | E35: =D35*1.1 -> 5900383.9 | F35: =E35*1.1 -> 6490422.3 | J35: Dev charges commercial area land component | L35: ='Feasibility Report'!T81/10000000 -> 0.010057074 | M35: =L35 -> 0.010057074 | N35: =M35 -> 0.010057074 | O35: =N35 -> 0.010057074 | P35: =O35 -> 0.010057074 | Q35: =L35 -> 0.010057074 | R35: =M35 -> 0.010057074 | S35: =N35 -> 0.010057074 | T35: =O35 -> 0.010057074 | U35: =P35 -> 0.010057074
B36: Brokerage 1 month | C36: Residential | D36: =C34*D29 -> 2419203.6 | J36: =K36*10.7639 -> 0 | L36: ='Feasibility Report'!T82/10000000 -> 0 | M36: =L36 -> 0 | N36: =M36 -> 0 | O36: =N36 -> 0 | P36: =O36 -> 0 | Q36: =L36 -> 0 | R36: =M36 -> 0 | S36: =N36 -> 0 | T36: =O36 -> 0 | U36: =P36 -> 0
B37: Brokerage 1 month | C37: Commercial | D37: =C35*D30 -> 446998.78 | J37: Labour welfare cess (total construction area * 0.01* rate) | L37: ='Feasibility Report'!T83/10000000 -> 0.35633579 | M37: =L37 -> 0.35633579 | N37: =M37 -> 0.35633579 | O37: =N37 -> 0.35633579 | P37: =O37 -> 0.35633579 | Q37: =L37 -> 0.35633579 | R37: =M37 -> 0.35633579 | S37: =N37 -> 0.35633579 | T37: =O37 -> 0.35633579 | U37: =P37 -> 0.35633579
B38: Shifting @ INR 30 k one time | D38: =30000*C31 -> 1110000 | J38: Open space Deficiency approx | L38: ='Feasibility Report'!T84/10000000 -> 15 | M38: =L38 -> 15 | N38: =M38 -> 15 | O38: =N38 -> 15 | P38: =O38 -> 15 | Q38: =L38 -> 15 | R38: =M38 -> 15 | S38: =N38 -> 15 | T38: =O38 -> 15 | U38: =P38 -> 15
D39: =SUM(D34:D38) -> 38370631 | E39: =SUM(E34:E38) -> 37833872 | F39: =SUM(F34:F38) -> 41617259 | J39: Staircase premium | L39: ='Feasibility Report'!T85/10000000 -> 5.0932358 | M39: =L39 -> 5.0932358 | N39: =M39 -> 5.0932358 | O39: =N39 -> 5.0932358 | P39: =O39 -> 5.0932358 | Q39: =L39 -> 5.0932358 | R39: =M39 -> 5.0932358 | S39: =N39 -> 5.0932358 | T39: =O39 -> 5.0932358 | U39: =P39 -> 5.0932358
C40: In crores | D40: =D39/10000000 -> 3.8370631 | E40: =E39/10000000 -> 3.7833872 | F40: =F39/10000000 -> 4.1617259 | J40: Water and Sewerage Charges (total construction area * rate) | L40: ='Feasibility Report'!T86/10000000 -> 0.57214763 | M40: =L40 -> 0.57214763 | N40: =M40 -> 0.57214763 | O40: =N40 -> 0.57214763 | P40: =O40 -> 0.57214763 | Q40: =L40 -> 0.57214763 | R40: =M40 -> 0.57214763 | S40: =N40 -> 0.57214763 | T40: =O40 -> 0.57214763 | U40: =P40 -> 0.57214763
C41: Total | F41: =SUM(D40:F40) -> 11.782176 | J41: Infra improvement charges (TDR to be purchased * rate) | L41: ='Feasibility Report'!T87/10000000 -> 0.13994301 | M41: =L41 -> 0.13994301 | N41: =M41 -> 0.13994301 | O41: =N41 -> 0.13994301 | P41: =O41 -> 0.13994301 | Q41: =L41 -> 0.13994301 | R41: =M41 -> 0.13994301 | S41: =N41 -> 0.13994301 | T41: =O41 -> 0.13994301 | U41: =P41 -> 0.13994301
J42: CFO Capitation fees (total construction area * rate) | L42: ='Feasibility Report'!T88/10000000 -> 0.1794973 | M42: =L42 -> 0.1794973 | N42: =M42 -> 0.1794973 | O42: =N42 -> 0.1794973 | P42: =O42 -> 0.1794973 | Q42: =L42 -> 0.1794973 | R42: =M42 -> 0.1794973 | S42: =N42 -> 0.1794973 | T42: =O42 -> 0.1794973 | U42: =P42 -> 0.1794973
J43: CFO service charges (total construction area * rate) | L43: ='Feasibility Report'!T89/10000000 -> 0.01794973 | M43: =L43 -> 0.01794973 | N43: =M43 -> 0.01794973 | O43: =N43 -> 0.01794973 | P43: =O43 -> 0.01794973 | Q43: =L43 -> 0.01794973 | R43: =M43 -> 0.01794973 | S43: =N43 -> 0.01794973 | T43: =O43 -> 0.01794973 | U43: =P43 -> 0.01794973
J44: Land under Assessment (Tax): (plot in possession *3.52%*3*rate) | L44: ='Feasibility Report'!T90/10000000 -> 1.9908893 | M44: =L44 -> 1.9908893 | N44: =M44 -> 1.9908893 | O44: =N44 -> 1.9908893 | P44: =O44 -> 1.9908893 | Q44: =L44 -> 1.9908893 | R44: =M44 -> 1.9908893 | S44: =N44 -> 1.9908893 | T44: =O44 -> 1.9908893 | U44: =P44 -> 1.9908893
J45: Additional development charges | L45: ='Feasibility Report'!T91/10000000 -> 1.4022367 | M45: =L45 -> 1.4022367 | N45: =M45 -> 1.4022367 | O45: =N45 -> 1.4022367 | P45: =O45 -> 1.4022367 | Q45: =L45 -> 1.4022367 | R45: =M45 -> 1.4022367 | S45: =N45 -> 1.4022367 | T45: =O45 -> 1.4022367 | U45: =P45 -> 1.4022367
J46: City survey office expenses | L46: ='Feasibility Report'!T92/10000000 -> 0.1 | M46: =L46 -> 0.1 | N46: =M46 -> 0.1 | O46: =N46 -> 0.1 | P46: =O46 -> 0.1 | Q46: =L46 -> 0.1 | R46: =M46 -> 0.1 | S46: =N46 -> 0.1 | T46: =O46 -> 0.1 | U46: =P46 -> 0.1
J47: Fitness centre Development Charges | L47: ='Feasibility Report'!T93/10000000 -> 0.16298355 | M47: =L47 -> 0.16298355 | N47: =M47 -> 0.16298355 | O47: =N47 -> 0.16298355 | P47: =O47 -> 0.16298355 | Q47: =L47 -> 0.16298355 | R47: =M47 -> 0.16298355 | S47: =N47 -> 0.16298355 | T47: =O47 -> 0.16298355 | U47: =P47 -> 0.16298355
J48: Solid Waste Management | L48: ='Feasibility Report'!T94/10000000 -> 0.1 | M48: =L48 -> 0.1 | N48: =M48 -> 0.1 | O48: =N48 -> 0.1 | P48: =O48 -> 0.1 | Q48: =L48 -> 0.1 | R48: =M48 -> 0.1 | S48: =N48 -> 0.1 | T48: =O48 -> 0.1 | U48: =P48 -> 0.1
J49: Pest control office ((total construction area * rate) | L49: ='Feasibility Report'!T95/10000000 -> 0.045996182 | M49: =L49 -> 0.045996182 | N49: =M49 -> 0.045996182 | O49: =N49 -> 0.045996182 | P49: =O49 -> 0.045996182 | Q49: =L49 -> 0.045996182 | R49: =M49 -> 0.045996182 | S49: =N49 -> 0.045996182 | T49: =O49 -> 0.045996182 | U49: =P49 -> 0.045996182
J50: Bank guamntee to BMC | L50: ='Feasibility Report'!T96/10000000 -> 0.12 | M50: =L50 -> 0.12 | N50: =M50 -> 0.12 | O50: =N50 -> 0.12 | P50: =O50 -> 0.12 | Q50: =L50 -> 0.12 | R50: =M50 -> 0.12 | S50: =N50 -> 0.12 | T50: =O50 -> 0.12 | U50: =P50 -> 0.12
J51: Civil aviation NOC | L51: ='Feasibility Report'!T97/10000000 -> 0.05 | M51: =L51 -> 0.05 | N51: =M51 -> 0.05 | O51: =N51 -> 0.05 | P51: =O51 -> 0.05 | Q51: =L51 -> 0.05 | R51: =M51 -> 0.05 | S51: =N51 -> 0.05 | T51: =O51 -> 0.05 | U51: =P51 -> 0.05
Q52: =L52 -> 0 | R52: =M52 -> 0 | S52: =N52 -> 0 | T52: =O52 -> 0 | U52: =P52 -> 0
J53: Legal Exp @INR 50000 for 37 units | L53: =50000*37/10000000 -> 0.185 | M53: =L53 -> 0.185 | N53: =M53 -> 0.185 | O53: =N53 -> 0.185 | P53: =O53 -> 0.185 | Q53: =L53 -> 0.185 | R53: =M53 -> 0.185 | S53: =N53 -> 0.185 | T53: =O53 -> 0.185 | U53: =P53 -> 0.185
J54: SD (New plot area*1.4*RR*6%) | L54: =(C8*1.4*122580*6%)/10000000 -> 1.5093962 | M54: =(C8*1.4*122580*6%)/10000000 -> 1.5093962 | N54: =M54 -> 1.5093962 | O54: =N54 -> 1.5093962 | P54: =O54 -> 1.5093962 | Q54: =L54 -> 1.5093962 | R54: =M54 -> 1.5093962 | S54: =N54 -> 1.5093962 | T54: =O54 -> 1.5093962 | U54: =P54 -> 1.5093962
J55: Miscellaneous Exp + Conti | L55: =10+2 -> 12 | M55: =10+2 -> 12 | N55: =10+2 -> 12 | O55: =10+2 -> 12 | P55: =10+2 -> 12 | Q55: =P55 -> 12 | R55: =Q55 -> 12 | S55: =R55 -> 12 | T55: =S55 -> 12 | U55: =T55 -> 12
J56: Salaries for 36 months @ 5 lakhs | L56: =0.05*36 -> 1.8 | M56: =0.05*36 -> 1.8 | N56: =0.05*36 -> 1.8 | O56: =0.05*36 -> 1.8 | P56: =0.05*36 -> 1.8 | Q56: =L56/3 -> 0.6 | R56: =M56/3 -> 0.6 | S56: =N56/3 -> 0.6 | T56: =O56/3 -> 0.6 | U56: =P56/3 -> 0.6
G57: =7/L12 -> 0.022118954 | J57: Marketing Exp @ 3% | L57: =L12*3% -> 9.4941196 | M57: =M12*3% -> 8.8598709 | N57: =N12*3% -> 8.7013087 | O57: =O12*3% -> 8.5427466 | P57: =P12*3% -> 8.3841844 | Q57: =L57/3 -> 3.1647065 | R57: =M57/3 -> 2.9532903 | S57: =N57/3 -> 2.9004362 | T57: =O57/3 -> 2.8475822 | U57: =P57/3 -> 2.7947281
J58: GST on Rehab as per PMC report INR 238440/Sq mt | L58: =C2*238440*5%/10000000 -> 2.8294403 | M58: =D2*238440*5%/10000000 -> 3.2197079 | N58: =E2*238440*5%/10000000 -> 3.3172748 | O58: =F2*238440*5%/10000000 -> 3.4148417 | P58: =G2*238440*5%/10000000 -> 3.5124086
J59: Compensation to existing owners
J60: Rental, Brokerage,Shifting | L60: =F41 -> 11.782176 | M60: =L60 -> 11.782176 | N60: =M60 -> 11.782176 | O60: =N60 -> 11.782176 | P60: =O60 -> 11.782176 | Q60: =L60/3 -> 3.9273921 | R60: =M60/3 -> 3.9273921 | S60: =N60/3 -> 3.9273921 | T60: =O60/3 -> 3.9273921 | U60: =P60/3 -> 3.9273921
J61: Corpus @ INR 1500 | L61: =D31*1500/10000000 -> 2.642703 | M61: =L61 -> 2.642703 | N61: =M61 -> 2.642703 | O61: =N61 -> 2.642703 | P61: =O61 -> 2.642703 | Q61: =L61/3 -> 0.880901 | R61: =M61/3 -> 0.880901 | S61: =N61/3 -> 0.880901 | T61: =O61/3 -> 0.880901 | U61: =P61/3 -> 0.880901
J62: Finance Cost for 12 Months @12% | L62: =Q63*12% -> 14.653437 | M62: =R63*12% -> 14.628067 | N62: =S63*12% -> 14.621725 | O62: =T63*12% -> 14.615382 | P62: =U63*12% -> 14.60904
J63: Total Cost | L63: =SUM(L16:L62) -> 206.31739 | M63: =SUM(M16:M62) -> 206.04804 | N63: =SUM(N16:N62) -> 205.9807 | O63: =SUM(O16:O62) -> 205.91336 | P63: =SUM(P16:P62) -> 205.84602 | Q63: =SUM(Q16:Q61) -> 122.11198 | R63: =SUM(R16:R61) -> 121.90056 | S63: =SUM(S16:S61) -> 121.84771 | T63: =SUM(T16:T61) -> 121.79485 | U63: =SUM(U16:U61) -> 121.742
J65: Net Profit | L65: =L12-L63 -> 110.15327 | M65: =M12-M63 -> 89.280996 | N65: =N12-N63 -> 84.062927 | O65: =O12-O63 -> 78.844859 | P65: =P12-P63 -> 73.626791 | Q65: =55000*1300/10000000 -> 7.15
J66: Income Tax @ 26% | L66: =L65*26% -> 28.63985 | M66: =M65*26% -> 23.213059 | N66: =N65*26% -> 21.856361 | O66: =O65*26% -> 20.499663 | P66: =P65*26% -> 19.142966 | Q66: =Q65*1.13 -> 8.0795
J67: PAT | L67: =L65-L66 -> 81.513419 | M67: =M65-M66 -> 66.067937 | N67: =N65-N66 -> 62.206566 | O67: =O65-O66 -> 58.345196 | P67: =P65-P66 -> 54.483825
O68: =M67-O67 -> 7.722741
J69: Return on Investment
J70: Total Investment for 1 year | L70: =Q63 -> 122.11198 | M70: =R63 -> 121.90056 | N70: =S63 -> 121.84771 | O70: =T63 -> 121.79485 | P70: =U63 -> 121.742
J71: Net Profit before tax | L71: =L65/L70 -> 0.90206768 | M71: =M65/M70 -> 0.7324084 | N71: =N65/N70 -> 0.68990159 | O71: =O65/O70 -> 0.64735788 | P71: =P65/P70 -> 0.60477724
J72: Net Profit before tax | L72: =L67/L70 -> 0.66753008 | M72: =M67/M70 -> 0.54198222 | N72: =N67/N70 -> 0.51052717 | O72: =O67/O70 -> 0.47904483 | P72: =P67/P70 -> 0.44753516
J74: Annual | L74: "@45% | M74: "@65% | N74: "@70% | O74: "@75% | P74: "@80%
J75: Net Profit before tax | L75: =L71/3 -> 0.30068923 | M75: =M71/3 -> 0.24413613 | N75: =N71/3 -> 0.2299672 | O75: =O71/3 -> 0.21578596 | P75: =P71/3 -> 0.20159241
J76: Net Profit after tax | L76: =L72/3 -> 0.22251003 | M76: =M72/3 -> 0.18066074 | N76: =N72/3 -> 0.17017572 | O76: =O72/3 -> 0.15968161 | P76: =P72/3 -> 0.14917839
J79: GST on rehab | L79: =C3*55000*10.764*5%/10000000 -> 2.18023 | M79: =D3*55000*10.764*5%/10000000 -> 3.1492211 | N79: =E3*55000*10.764*5%/10000000 -> 3.3914689 | O79: =F3*55000*10.764*5%/10000000 -> 3.6337166 | P79: =G3*55000*10.764*5%/10000000 -> 3.8759644

Sheet Feasibility Report
M1: Feasibility Report For Dharti CHS Ltd., situated at Versova, Mumbai.
C2: B)AREA OF PLOT IN POSSESSION | E2: 10.7639 | P2: Typed Figures
O3: "45% additional area | Q3: "65% additional area | R3: "70% additioanl area | S3: "75% additional area | T3: "80% additional area
D4: Area in Sq mt | E4: Area in Sq ft | M4: Particulars | N4: Area in Sq mt | O4: Area in Sq mt | P4: Area in Sq ft | Q4: Area in Sq mt | R4: Area in Sq mt | S4: Area in Sq mt | T4: Area in Sq mt
B5: 1) | C5: A)AREA OF PLOT | D5: 1538.9 | E5: =D5*10.7639-9.76 -> 16554.806 | G5: 1538.90*10.7639-9.76 | K5: A | M5: AREA OF PLOT | O5: 1538.9 | P5: =O5*10.7639-9.76 -> 16554.806 | Q5: 1538.9 | R5: =Q5 -> 1538.9 | S5: =R5 -> 1538.9 | T5: =S5 -> 1538.9
C6: B)AREA OF PLOT IN POSSESSION | D6: =D5 -> 1538.9 | E6: =E5 -> 16554.806 | M6: AREA OF PLOT IN POSSESSION | O6: =O5 -> 1538.9 | P6: =P5 -> 16554.806 | Q6: =Q5 -> 1538.9 | R6: =Q6 -> 1538.9 | S6: =R6 -> 1538.9 | T6: =S6 -> 1538.9
B8: 2) | C8: Deduction for | M8: Old Plot area approve plan | N8: 1635
C9: A)30 MT DP ROAD | D9: 0 | M9: Less: Old set back Area (Road width 18.3m) | N9: 108.14
C10: B)AMENITY SPACE | D10: =SUM(D9:D9) -> 0 | M10: Old Net Plot Area | N10: =N8-N9 -> 1526.86
C11: C)AREA UNDER ENCROCHMENT | D11: 0
C12: TOTAL DEDUCTION | D12: 0 | M12: Less: New set back Area | N12: 73
M13: New Net Plot Area | N13: =O6-N12 -> 1465.9
B14: 3) | C14: BALANCE AREA OF PLOT(1 ,2) | D14: =D6-D12 -> 1538.9 | E14: =E6-G12 -> 16554.806
C15: Deduction Recreation Ground as per rule @15% | D15: 0 | M15: Existing BUA | N15: 1634.33 | W15: As per existing approved plan
C16: Net area of plot | D16: =D14-D15 -> 1538.9 | E16: =E14-E15 -> 16554.806
C17: Additional for floor space index road | D17: 0 | K17: B | M17: Existing Balcony Area | O17: 129.329 | P17: =O17*10.7639+0.02 -> 1392.1044 | Q17: 129.329 | R17: =Q17 -> 129.329 | S17: =R17 -> 129.329 | T17: =S17 -> 129.329 | W17: 278.42*5
B18: 4) | C18: TOTAL USABLE CARPET AREA OF SOCIETY | D18: =D5-D17 -> 1538.9 | E18: =E5-E17 -> 16554.806 | M18: Existing CA Residential Flats: 33 | O18: 1498.33 | P18: =O18*10.7639+0.13 -> 16128.004 | Q18: 1498.33 | R18: =Q18 -> 1498.33 | S18: =R18 -> 1498.33 | T18: =S18 -> 1498.33
M19: Existing CA Commercial Shops: 4 | O19: 138.424 | P19: =O19*10.7639+0.02 -> 1490.0021 | Q19: 138.424 | R19: =Q19 -> 138.424 | S19: =R19 -> 138.424 | T19: =S19 -> 138.424
B20: 5) | C20: Maximum permissible FSI as per Table 6G-UDCPR | M20: Total Existing Carpet Area | O20: =O18+O19 -> 1636.754 | P20: =O20*10.7639 -> 17617.856 | Q20: =Q18+Q19 -> 1636.754 | R20: =Q20 -> 1636.754 | S20: =R20 -> 1636.754 | T20: =S20 -> 1636.754
B21: a) | C21: Basic FSI of 1.1 (2504.22 *1.1) | D21: =D18*1.1 -> 1692.79 | E21: =D21*10.7639-10.74 -> 18210.282 | G21: Flats | M21: Existing BUA with balcony (1636.75 * 1.2) | O21: =+O20*1.2-0.002236 -> 1964.1026 | P21: =O21*10.7639 -> 21141.404 | Q21: =+Q20*1.2-0.002236 -> 1964.1026 | R21: =R20*1.2 -> 1964.1048 | S21: =S20*1.2 -> 1964.1048 | T21: =T20*1.2 -> 1964.1048
B22: b) | C22: 15 sq.mt PER TENANT INCENTIVE - UDCPR 7.6.1.(i) (____ X 15)-IF APPLICABLE | D22: 3756.33 | E22: =D22*10.7639-14.65 -> 40418.11 | G22: =D22/15 -> 250.422
B23: c) | C23: F.S.I ON PAYMENT OF PREMIUM - 0.5 (2504.22X0.5) for 18.43 m wide road as per old DP | D23: =D6*0.5 -> 769.45 | E23: =D23*10.7639-4.89 -> 8277.3929 | K23: C | M23: Permissible FSI :
B24: d) | C24: T.D.R TO BE PURCHASED - 6.75 (2504.22X0.9) for 18.43 m wide road as per old DP | D24: =D6*0.9 -> 1385.01 | E24: =D24*10.7639-8.79 -> 14899.319 | M24: 2.4 proposed BUA (2.4 * 1465.9) (Plot area * 2.4) | O24: =N13*2.4 -> 3518.16 | P24: =O24*10.7639 -> 37869.122 | Q24: =N13*2.4 -> 3518.16 | R24: =N13*2.4 -> 3518.16 | S24: =N13*2.4 -> 3518.16 | T24: =N13*2.4 -> 3518.16 | W24: as per road with
C25: TOTAL FSI | D25: =SUM(D21:D24) -> 7603.58 | E25: =SUM(E21:E24) -> 81805.105 | F25: =E25/D25 -> 10.758762 | G25: =SUM(G21:G24)+0.01 -> 250.432 | M25: Add: Set back Area (2 * 73) (Set back area * 2) | O25: =N12*2 -> 146 | P25: =O25*10.7639 -> 1571.5294 | Q25: =N12*2 -> 146 | R25: =N12*2 -> 146 | S25: =N12*2 -> 146 | T25: =N12*2 -> 146
M26: Proposed BUA | O26: =SUM(O24:O25) -> 3664.16 | P26: =SUM(P24:P25) -> 39440.652 | Q26: =SUM(Q24:Q25) -> 3664.16 | R26: =SUM(R24:R25) -> 3664.16 | S26: =SUM(S24:S25) -> 3664.16 | T26: =SUM(T24:T25) -> 3664.16
B27: e) | C27: F.S.I CONSUMED FOR RESIDENTIAL=72 | D27: 2727.3 | E27: =D27*10.7639-10.61 -> 29345.774 | F27: =E27/D27 -> 10.76001 | W27: Sec 33 -11 | X27: SRA scheme
B28: f) | C28: ANCILLARY F.S.I- 0.6 ON RESIDENTIAL AREA (2727.3*0.6) | D28: =D27*0.6 -> 1636.38 | E28: =D28*10.7639-6.37 -> 17607.461 | I28: *** | L28: a | M28: Proposed BUA Rehab ( Existing builtup area * additional area offered) | O28: =O21*1.45 -> 2847.9487 | P28: =O28*10.7639 -> 30655.035 | Q28: =Q21*1.65 -> 3240.7692 | R28: =R21*1.7 -> 3338.9782 | S28: =S21*1.75 -> 3437.1834 | T28: =T21*1.8 -> 3535.3886 | W28: 45% Additional Area
B29: g) | C29: TOTAL B.U.A FOR RESIDENTIAL PURPOSE (E+F) INCLUDING BALCON | D29: =D27+D28 -> 4363.68 | E29: =E27+E28 -> 46953.235 | L29: b | M29: Rehab Fungible Area (existing BUA * 0.35) | O29: =N15*0.35 -> 572.0155 | P29: =O29*10.7639 -> 6157.1176 | Q29: =N15*0.35 -> 572.0155 | R29: =N15*0.35 -> 572.0155 | S29: =N15*0.35 -> 572.0155 | T29: =N15*0.35 -> 572.0155
L30: c | M30: Proposed Rehab CA (2847.948718 / 1.2) | O30: =O28/1.2 -> 2373.2906 | P30: =O30*10.7639 -> 25545.863 | Q30: =Q28/1.2 -> 2700.641 | R30: =R28/1.2 -> 2782.4818 | S30: =S28/1.2 -> 2864.3195 | T30: =T28/1.2 -> 2946.1572
B31: h) | C31: F.S.I TO BE CONSUMED FOR COMMERCIAL 12 | D31: 220.66 | E31: =D31*10.7639+0.04 -> 2375.2022 | F31: 2375.2
B32: i) | C32: ANCILLARY F.SI- 0.8 ON COMMERCIAL AREA (220.66*0.8) | D32: =D31*0.8 -> 176.528 | E32: =D32*10.7639+0.01 -> 1900.1397 | K32: D | M32: Govt FSI : plot area x 0.5 (0.5 * 1465.9) (Plot area * 0.5) | O32: =N13*0.5 -> 732.95 | P32: =O32*10.7639 -> 7889.4005 | Q32: =N13*0.5 -> 732.95 | R32: =N13*0.5 -> 732.95 | S32: =N13*0.5 -> 732.95 | T32: =N13*0.5 -> 732.95 | W32: Purchase from BMC
B33: j) | C33: TOTAL B.U.A FOR COMMERCIAL PURPOSE (H+I) | D33: =D31+D32 -> 397.188 | E33: =E31+E32 -> 4275.3419
K34: E | M34: TDR: plot area x 0.9 (0.9 * 1465.9) (Plot area * 0.9) | O34: =N13*0.9 -> 1319.31 | P34: =O34*10.7639 -> 14200.921 | Q34: =N13*0.9 -> 1319.31 | R34: =N13*0.9 -> 1319.31 | S34: =N13*0.9 -> 1319.31 | T34: =N13*0.9 -> 1319.31
C35: MAX PERMISSIBLE FSI (g+j) | D35: =D29+D33 -> 4760.868 | E35: =E29+E33+17.45 -> 51246.027 | L35: a | M35: TDR to be purchased (1319.31 sqm - incentive: 33 Flats x 10 sqm - 108.14 sqm) | O35: =O34-(33*10)-108.14 -> 881.17 | P35: =O35*10.7639 -> 9484.8258 | Q35: =Q34-(33*10)-108.14 -> 881.17 | R35: =R34-(33*10)-108.14 -> 881.17 | S35: =S34-(33*10)-108.14 -> 881.17 | T35: =T34-(33*10)-108.14 -> 881.17 | W35: Need to ask 108.14 sqmt
C37: CARPET AREA 72+12 | K37: F | M37: Proposed bua rehab commer. (exis carpet area comme * 1.2 * 1.4) | O37: =(O19+0.0043776)*1.2*1.4-0.00672 -> 232.55295 | P37: =O37*10.7639 -> 2503.1767 | Q37: =(Q19+0.0043776)*1.2*1.4-0.00672 -> 232.55295 | R37: =(R19+0.0043776)*1.2*1.4-0.00672 -> 232.55295 | S37: =(S19+0.0043776)*1.2*1.4-0.00672 -> 232.55295 | T37: =(T19+0.0043776)*1.2*1.4-0.00672 -> 232.55295 | V37: 0.006720068
B38: a) | C38: RESIDENTIAL CARPET AREA (g *0.78) | D38: =D29*0.78 -> 3403.6704 | E38: =D38*10.7639 -> 36636.768
B39: b) | C39: COMMERCIAL CARPET AREA (Ij * 0.82) | D39: =D33*0.82 -> 325.69416 | E39: =D39*10.7639 -> 3505.7394 | K39: G | M39: 33f20b : permissible BUA (4 * 1538.9) (plot area in Posession*4) | O39: =O6*4 -> 6155.6 | P39: =O39*10.7639 -> 66258.263 | Q39: =Q6*4 -> 6155.6 | R39: =O6*4 -> 6155.6 | S39: =O6*4 -> 6155.6 | T39: =O6*4 -> 6155.6
C40: TOTAL AVAILABLE CARPET AREA IN PROJECT | D40: =SUM(D38:D39) -> 3729.3646 | E40: =SUM(E38:E39) -> 40142.507 | M40: Less: BUA under 33/7b | O40: 3664.16 | P40: =O40*10.7639 -> 39440.652 | Q40: 3664.16 | R40: 3664.16 | S40: 3664.16 | T40: 3664.16
C41: EXISTING CARPET AREA OF THE SOCIETY | M41: Balance BUA | O41: =O39-O40 -> 2491.44 | P41: =O41*10.7639 -> 26817.611 | Q41: =Q39-Q40 -> 2491.44 | R41: =R39-R40 -> 2491.44 | S41: =S39-S40 -> 2491.44 | T41: =T39-T40 -> 2491.44
B42: a) | C42: RESIDENTIAL CARPET AREA (72NO.S OF RESIDENTIAL TENANTS) | D42: 3840.04 | E42: =D42*10.7639+0.4 -> 41334.207
B43: b) | C43: COMMERCIAL CARPET AREA -12 | D43: 337.61 | E43: =D43*10.7639+0.06 -> 3634.0603 | L43: a | M43: PAP BUA to be given to BMC (0.5 * 2491.44) | O43: =O41*0.5 -> 1245.72 | P43: =O43*10.7639 -> 13408.806 | Q43: =Q41*0.5 -> 1245.72 | R43: =R41*0.5 -> 1245.72 | S43: =S41*0.5 -> 1245.72 | T43: =T41*0.5 -> 1245.72 | W43: The built-up area (BUA) designated for Project Affected Persons (PAP) shall be handed over to the Brihanmumbai Municipal Corporation (BMC)
C44: TOTAL EXISTING CARPET AREA | D44: =SUM(D42:D43) -> 4177.65 | E44: =D44*10.7639+0.45 -> 44968.257 | L44: b | M44: BUA on plot under 33/20b (2*1245.72) | O44: =O43*2 -> 2491.44 | P44: =O44*10.7639 -> 26817.611 | Q44: =Q43*2 -> 2491.44 | R44: =R43*2 -> 2491.44 | S44: =S43*2 -> 2491.44 | T44: =T43*2 -> 2491.44
D45: Units | E45: Sq ft
C46: Residential | D46: 72 | E46: =E42 -> 41334.207 | K46: H | M46: Total BUA proposed (plot area in Posession*4) | O46: =O6*4 -> 6155.6 | P46: =O46*10.7639 -> 66258.263 | Q46: =Q44+Q40 -> 6155.6 | R46: =R6*4 -> 6155.6 | S46: =S6*4 -> 6155.6 | T46: =T6*4 -> 6155.6
C47: Commercial | D47: 12 | E47: =E43 -> 3634.0603 | K47: I | M47: Fungible Area (0.35 * 6155.60) (BUA * 0.35) | O47: =O46*0.35 -> 2154.46 | P47: =O47*10.7639 -> 23190.392 | Q47: =Q46*0.35 -> 2154.46 | R47: =R46*0.35 -> 2154.46 | S47: =S46*0.35 -> 2154.46 | T47: =T46*0.35 -> 2154.46
K48: J | M48: Total BUA with Fungible (6155.60 + 2154.46) | O48: =O46+O47 -> 8310.06 | P48: =O48*10.7639 -> 89448.655 | Q48: =Q46+Q47 -> 8310.06 | R48: =R46+R47 -> 8310.06 | S48: =S46+S47 -> 8310.06 | T48: =T46+T47 -> 8310.06
C49: Rental ( Higher side) | E49: Y1 | F49: Y2 | G49: Y3 | K49: K | M49: Sale Fungible Area (Funglible area - Rehab Fungible) | O49: =O47-O29 -> 1582.4445 | P49: =O49*10.7639 -> 17033.274 | Q49: =Q47-Q29 -> 1582.4445 | R49: =R47-R29 -> 1582.4445 | S49: =S47-S29 -> 1582.4445 | T49: =T47-T29 -> 1582.4445 | V49: =O48/O5 -> 5.4 | W49: =P48/P5 -> 5.4031836
C50: Brokerage 1 month | D50: Residential | E50: =D46*25000 -> 1800000
C51: Brokerage 1 month | D51: Commercial | E51: =D47*40000 -> 480000 | K51: L | M51: Total Construction Area (8310.06 * 1.35) (BUA *1.35 TIMES) | O51: =O48*1.35 -> 11218.581 | P51: =O51*10.7639 -> 120755.68 | Q51: =Q48*1.35 -> 11218.581 | R51: =R48*1.35 -> 11218.581 | S51: =S48*1.35 -> 11218.581 | T51: =T48*1.35 -> 11218.581
C52: Shifting @ INR 20 k one time | E52: =#REF!*20000 -> #REF! | W52: 2.4 | X52: Basic
E53: =SUM(E50:E52) -> #REF! | F53: =SUM(F50:F52) -> 0 | G53: =SUM(G50:G52) -> 0 | K53: M | M53: Sale BUA (total BUA -Rehal BUA) | O53: =O48-O28 -> 5462.1113 | P53: =O53*10.7639 -> 58793.62 | Q53: =Q48-Q28 -> 5069.2908 | R53: =R48-R28 -> 4971.0818 | S53: =S48-S28 -> 4872.8766 | T53: =T48-T28 -> 4774.6714 | W53: 1.6 | X53: additional
D54: In crores | E54: =E53/10000000 -> #REF! | F54: =F53/10000000 -> 0 | G54: =G53/10000000 -> 0
D55: Total | G55: =SUM(E54:G54) -> #REF! | K55: N | M55: Sale Carpet Area ( BUA/1.1) | O55: =O53/1.1 -> 4965.5557 | P55: =O55*10.7639 -> 53448.745 | Q55: =Q53/1.1 -> 4608.4462 | R55: =R53/1.1 -> 4519.1653 | S55: =S53/1.1 -> 4429.8878 | T55: =T53/1.1 -> 4340.6103
M57: Description | N57: Sq. Mt | O57: Sq. Ft | R57: Rate | S57: Units | T57: Amount | U57: Initial Investment
M59: Cost:
J60: C | K60: 1 | M60: Construction Cost: | N60: =O51 -> 11218.581 | O60: =N60*10.7639+0.17 -> 120755.85 | P60: 0 | Q60: 0 | R60: 4000 | S60: per/sqft | T60: =O60*R60-4.58 -> 4.8302341e+08 | U60: =T60/3 -> 1.610078e+08
J61: C | K61: =+K60+1 -> 2 | M61: Podium parking RCC work | N61: 3324.024 | O61: =N61*10.7639+0.33 -> 35779.792 | P61: 0 | Q61: 0 | R61: 2500 | S61: per/sqft | T61: =O61*R61+6.01 -> 89449486 | U61: =T61/3 -> 29816495
J62: C | K62: =+K61+1 -> 3 | M62: GST on construction | N62: 0 | O62: 0 | P62: 0 | Q62: 0.05 | R62: 5.724729e+08 | S62: - | T62: =(T60+T61)*0.05 -> 28623645 | U62: =T62/3 -> 9541215
J63: C | K63: =+K62+1 -> 4 | M63: Escalation in construction cost | N63: 0 | O63: 0 | P63: 0 | Q63: 0.05 | R63: 5.724729e+08 | S63: - | T63: =(T60+T61)*0.05 -> 28623645 | U63: =T63/3 -> 9541215 | V63: 89449486
J64: C | K64: =+K63+1 -> 5 | M64: Consultants @ 6% | N64: 0 | O64: 0 | P64: 0 | Q64: 0.06 | R64: 5.724729e+08 | S64: - | T64: =(T60+T61)*0.06 -> 34348374 | U64: =T64/3 -> 11449458 | V64: =T61-V63 -> 0.0039999932
I65: =R65/10.764 -> 11387.96 | J65: C | K65: =+K64+1 -> 6 | M65: TDR Cost : slum TDR | N65: =O35 -> 881.17 | O65: 0 | P65: 0.2 | Q65: 0.85 | R65: 122580 | S65: per/sqmt | T65: =N65*P65*Q65*R65 -> 18362349 | U65: =T65 -> 18362349
J66: C | K66: =+K65+1 -> 7 | M66: General TDR | N66: =O35 -> 881.17 | O66: 0 | P66: 0.8 | Q66: 0.65 | R66: 122580 | S66: per/sqmt | T66: =N66*P66*Q66*R66 -> 56167186 | U66: =T66 -> 56167186
J67: C | K67: =+K66+1 -> 8 | M67: Stamp duty on TDR | N67: 0 | O67: 0 | P67: 0 | Q67: 0.03 | R67: 74529535 | S67: - | T67: =(T65+T66)*0.03 -> 2235886 | U67: =T67 -> 2235886 | V67: =N65*O65*Q65 -> 0
J68: C | K68: =+K67+1 -> 9 | M68: 50 % Government FSI | N68: =O32 -> 732.95 | O68: 0 | P68: 0 | Q68: 0.5 | R68: 122580 | S68: per/sqmt | T68: =N68*Q68*R68 -> 44922506 | U68: =T68 -> 44922506 | V68: =V67*R65 -> 0
J69: C | K69: =+K68+1 -> 10 | M69: Cost of Sale Fungible Area Rest | N69: =O49 -> 1582.4445 | O69: 0 | P69: 0 | Q69: 0.5 | R69: 122580 | S69: per/sqmt | T69: =N69*Q69*R69 -> 96988023 | U69: =T69/3 -> 32329341
K70: =+K69+1 -> 11 | M70: Commercial sale fungible area | N70: 0 | O70: 0 | P70: 0 | Q70: 0.6 | R70: 122580 | S70: per/sqmt | T70: 0 | U70: =T70/3 -> 0
I71: =T71/10.764 -> 19674136 | J71: C | K71: =+K70+1 -> 12 | M71: PAP purchase cost approx | N71: =O43 -> 1245.72 | O71: 0 | P71: 0 | Q71: 0 | R71: 170000 | S71: per/sqmt | T71: =N71*R71 -> 2.117724e+08 | U71: =T71 -> 2.117724e+08 | V71: The built-up area (BUA) designated for Project Affected Persons (PAP) shall be handed over to the Brihanmumbai Municipal Corporation (BMC)
I72: =R71/10.764 -> 15793.385 | J72: C | K72: =+K71+1 -> 13 | M72: Stamp duty on PAP | N72: 0 | O72: 0 | P72: 0 | Q72: 0.06 | R72: 211772400 | S72: - | T72: =T71*0.06 -> 12706344 | U72: =T72 -> 12706344
J73: C | K73: =+K72+1 -> 14 | M73: Difference in premium RR approx | N73: =O43 -> 1245.72 | O73: 0 | P73: 0 | Q73: 0.4 | R73: 20000 | S73: per/sqmt | T73: =N73*Q73*R73 -> 9965760 | U73: =T73/3 -> 3321920 | V73: The premium (or loading) applied to the Ready Reckoner (RR) rate—the government-assessed property value used for stamp duty and registration
K74: 15 | M74: Municipal Expenses | N74: - | O74: - | P74: - | Q74: - | R74: - | S74: - | T74: 0 | U74: =T74/3 -> 0
J75: C | L75: a | M75: Scrutiny fees (Total BUA with fungible FSI) * RR | N75: =O48 -> 8310.06 | O75: =N75*10.7639+0.13 -> 89448.785 | P75: 0 | Q75: 0 | R75: 300 | S75: per/sqmt | T75: =R75*N75 -> 2493018 | U75: =T75 -> 2493018
J76: C | L76: b | M76: I.O.D Deposit | N76: =O48 -> 8310.06 | O76: =N76*10.7639+0.13 -> 89448.785 | P76: 0 | Q76: 0 | R76: 1 | S76: per/sqft | T76: =R76*O76 -> 89448.785 | U76: =T76 -> 89448.785
J77: C | L77: c | M77: Debris Deposit (Rs. 45,000 max) | N77: =O48 -> 8310.06 | O77: =N77*10.7639+0.13 -> 89448.785 | P77: 0 | Q77: 0 | R77: 2 | S77: per/sqft | T77: 45000 | U77: =T77 -> 45000
J78: C | L78: d | M78: Development charges 4% for built up area | N78: 8077.51 | O78: 0 | P78: 0 | Q78: 0.04 | R78: 122580 | S78: per/sqmt | T78: =N78*Q78*R78-14.48 -> 39605633 | U78: =T78 -> 39605633
J79: C | L79: e | M79: Dev charges on commercial area | N79: =O37 -> 232.55295 | O79: 0 | P79: 0 | Q79: 0.08 | R79: 122580 | S79: per/sqmt | T79: 0 | U79: =T79 -> 0
J80: C | L80: f | M80: Development charges 1% of land component (New Plot area * 1%) | N80: =N13 -> 1465.9 | O80: 0 | P80: 0 | Q80: 0.01 | R80: 122580 | S80: per/sqmt | T80: =N80*Q80*R80 -> 1796900.2 | U80: =T80 -> 1796900.2
J81: C | L81: g | M81: Dev charges commercial area land component | N81: 41.02 | O81: 0 | P81: 0 | Q81: 0.02 | R81: 122580 | S81: per/sqmt | T81: =N81*Q81*R81+6.11 -> 100570.74 | U81: =T81 -> 100570.74
M82: =N82*10.7639 -> 15778.801 | N82: =N13 -> 1465.9 | O82: 8310.06 | P82: 0 | Q82: 232.55 | R82: 41.02 | S82: - | T82: 0 | U82: =T82 -> 0
J83: C | L83: h | M83: Labour welfare cess (total construction area * 0.01* rate) | N83: =O51 -> 11218.581 | O83: 0 | P83: 0 | Q83: 0.01 | R83: 31763 | S83: per/sqmt | T83: =N83*Q83*R83 -> 3563357.9 | U83: =T83 -> 3563357.9
L84: i | M84: Open space Deficiency approx | N84: 0 | O84: 0 | P84: 0 | Q84: 0 | R84: 0 | S84: - | T84: 150000000 | U84: =T84 -> 150000000
I85: assumed 20 floors | J85: C | L85: j | M85: Staircase premium | N85: 1662.01 | O85: 0 | P85: 0 | Q85: 0.25 | R85: 122580 | S85: per/sqmt | T85: =N85*Q85*R85+61.29 -> 50932358 | U85: =T85 -> 50932358
J86: C | L86: k | M86: Water and Sewerage Charges (total construction area * rate) | N86: =O51 -> 11218.581 | O86: 0 | P86: 0 | Q86: 0 | R86: 510 | S86: per/sqmt | T86: =N86*R86 -> 5721476.3 | U86: =T86 -> 5721476.3
J87: C | L87: l | M87: Infra improvement charges (TDR to be purchased * rate) | N87: =O35 -> 881.17 | O87: 0 | P87: 0 | Q87: 0.05 | R87: 31763 | S87: per/sqmt | T87: =N87*Q87*R87 -> 1399430.1 | U87: =T87 -> 1399430.1
J88: C | L88: m | M88: CFO Capitation fees (total construction area * rate) | N88: =O51 -> 11218.581 | O88: 0 | P88: 0 | Q88: 0 | R88: 160 | S88: per/sqmt | T88: =N88*R88 -> 1794973 | U88: =T88 -> 1794973
J89: C | L89: n | M89: CFO service charges (total construction area * rate) | N89: =O51 -> 11218.581 | O89: 0 | P89: 0 | Q89: 0 | R89: 16 | S89: per/sqmt | T89: =N89*R89 -> 179497.3 | U89: =T89 -> 179497.3
J90: C | L90: o | M90: Land under Assessment (Tax): (plot in possession *3.52%*3*rate) | N90: =O6 -> 1538.9 | O90: 0 | P90: 0.0352 | Q90: 3 | R90: 122580 | S90: per/yr & per/sqmt | T90: =N90*P90*Q90*R90-11318.3 -> 19908893 | U90: =T90 -> 19908893
I91: Std premiums | J91: C | L91: p | M91: Additional development charges | N91: 2859.84 | O91: 0 | P91: 0 | Q91: 0.04 | R91: 122580 | S91: per/sqmt | T91: =N91*Q91*R91 -> 14022367 | U91: =T91 -> 14022367
J92: C | L92: q | M92: City survey office expenses | N92: 0 | O92: 0 | P92: 0 | Q92: 0 | R92: 0 | S92: per/sqmt | T92: 1000000 | U92: =T92 -> 1000000 | V92: 19908893 | W92: 11318.3
J93: C | L93: r | M93: Fitness centre Development Charges | N93: 332.4 | O93: 0 | P93: 0 | Q93: 0.04 | R93: 122580 | S93: per/sqmt | T93: =N93*Q93*R93+11.77 -> 1629835.4 | U93: =T93 -> 1629835.4
J94: C | L94: s | M94: Solid Waste Management | N94: 0 | O94: 0 | P94: 0 | Q94: 0 | R94: 0 | S94: - | T94: 1000000 | U94: =T94 -> 1000000
J95: C | L95: t | M95: Pest control office ((total construction area * rate) | N95: =O51 -> 11218.581 | O95: 0 | P95: 0 | Q95: 0 | R95: 41 | S95: per/sqmt | T95: =N95*R95 -> 459961.82 | U95: =T95 -> 459961.82
J96: C | L96: u | M96: Bank guamntee to BMC | N96: 0 | O96: 0 | P96: 0 | Q96: 0 | R96: 0 | S96: - | T96: 1200000 | U96: =T96 -> 1200000
J97: C | L97: v | M97: Civil aviation NOC | N97: 0 | O97: 0 | P97: 0 | Q97: 0 | R97: 0 | S97: - | T97: 500000 | U97: =T97 -> 500000
J98: C | K98: 16 | M98: Legal expenses | N98: 0 | O98: 0 | P98: 0 | Q98: 0 | R98: 0 | S98: - | T98: 0 | U98: =T98 -> 0
J99: C | L99: a | M99: Legal consultant | N99: 0 | O99: 0 | P99: 0 | Q99: =33+4 -> 37 | R99: 50000 | S99: per/nos | T99: =Q99*R99 -> 1850000 | U99: =T99/3 -> 616666.67 | V99: Existing Residential Flats & Shop
I100: plot area *1.4* RR | J100: C | L100: b | M100: Stamp duty | N100: 0 | O100: 0 | P100: 0 | Q100: 0.06 | R100: 0 | S100: per/sqmt | T100: 15000000 | U100: =T100/3 -> 5000000 | V100: =T100/Q100 -> 250000000
K101: 17 | M101: Miscellenious Expenses + Contingencies | N101: 0 | O101: 0 | P101: 0 | Q101: 0 | R101: 0 | S101: - | T101: =100000000+20000000 -> 120000000 | U101: =T101/3 -> 40000000 | V101: =T100/Q100 -> 250000000
K102: 18 | M102: Corpus to members | N102: 0 | O102: =P20+0.14 -> 17617.996 | P102: 0 | Q102: 0 | R102: 1500 | S102: per/sqft | T102: =O102*R102 -> 26426995 | U102: =T102/3 -> 8808998.2
K103: 19 | M103: Transit Accommodation residential | N103: =O18 -> 1498.33 | O103: =N103*10.7639+0.13 -> 16128.004 | P103: 0 | Q103: 36 | R103: 150 | S103: per/sqft | T103: =O103*Q103*R103 -> 87091223 | U103: =T103/3 -> 29030408
I104: 250 can be offered | M104: Commercial | N104: =O19 -> 138.424 | O104: =N104*10.7639+0.02 -> 1490.0021 | P104: 0 | Q104: 36 | R104: 300 | S104: per/sqft | T104: =O104*Q104*R104 -> 16092023 | U104: =T104/3 -> 5364007.5
...

Sheet Area & Cmpsn to Exstng Mmbr
B2: Area to Existing Members
B3: Particulars | C3: Sqmt | D3: Sqft
B4: Existing Balcony Area | C4: 129.329 | D4: =C4*10.7639+0.02 -> 1392.1044
B5: Existing CA Residential Flats: 33 | C5: 1498.33 | D5: =C5*10.7639+0.13 -> 16128.004
B6: Existing CA Commercial Shops: 4 | C6: 138.424 | D6: =C6*10.7639+0.02 -> 1490.0021
B7: Toal Existing Carpet Area | C7: =C5+C6 -> 1636.754 | D7: =C7*10.7639 -> 17617.856
B8: Existing BUA with balcony (1636.75 * 1.2) | C8: =+C7*1.2-0.002236 -> 1964.1026 | D8: =C8*10.7639 -> 21141.404
B9: Additiona Area (1964.1 * 0.45) | C9: =C8*0.45 -> 883.84615 | D9: =C9*10.7639 -> 9513.6316
B10: Proposed BUA Rehab (1.45 * 1964.102564) | C10: =C8+C9 -> 2847.9487 | D10: =C10*10.7639 -> 30655.035
B12: Compensation or Cost to Existing Members
B13: Particulars | C13: Sqmt | D13: Sqft | E13: No. of Members | F13: No. of Months | G13: Cost per Unit | H13: Total Cost
B14: Corpus to members | C14: 0 | D14: ='Area & Cmpsn to Exstng Mmbr'!D7+0.14 -> 17617.996 | E14: 0 | F14: 0 | G14: 1500 | H14: =D14*G14 -> 26426995
B15: Transit Accommodation residential | C15: ='Feasibility Report'!N103 -> 1498.33 | D15: =C15*10.7639+0.13 -> 16128.004 | E15: 0 | F15: 36 | G15: 125 | H15: =D15*F15*G15 -> 72576019
B16: Commercial | C16: 138.424 | D16: 1490.0021 | E16: 0 | F16: 36 | G16: 200 | H16: =D16*F16*G16 -> 10728015
B17: One month Brokerage (transit) | C17: 0 | D17: 17617.996 | E17: 0 | F17: 1 | G17: 125 | H17: =D17*F17*G17 -> 2202249.5
B18: Shifting Charges | C18: 0 | D18: 0 | E18: 37 | F18: 0 | G18: 30000 | H18: =E18*G18 -> 1110000
B19: Total | H19: =SUM(H14:H18) -> 1.1304328e+08
E24: Total Cost | F24: Admin / marketing / site expenses | G24: Interest On Initial Investment | H24: Total Cost other than Admin / marketing / site expenses
E25: 1.9128194e+09 | F25: 70000000 | G25: 150000000 | H25: =E25-F25-G25 -> 1.6928194e+09
B27: Total Finance Cost
B28: Particulars | C28: Amount
B29: TDR Cost : slum TDR | C29: 18362349
B30: General TDR | C30: 56167186
B31: Stamp duty on TDR | C31: 2235886
B32: 50 % Government FSI | C32: 44922506
B33: Total Municipal Expense | C33: =SUM('Feasibility Report'!T75:T97) -> 2.9744272e+08
B34: Total Other Cost | C34: =(H25-SUM(C29:C33))/3 -> 4.2456291e+08
B35: Admin / marketing / site expenses | C35: ='Feasibility Report'!T116*0.04 -> 1.219074e+08
C36: =SUM(C29:C35) -> 9.6560096e+08
B38: Finance cost @ 12% | C38: =C36*0.12 -> 1.1587212e+08
